Metadata-Version: 1.0
Name: autosub
Version: 0.3.5
Summary: Auto-generates subtitles for any video or audio file
Home-page: https://github.com/agermanidis/autosub
Author: Anastasis Germanidis
Author-email: agermanidis@gmail.com
License: The MIT License (MIT)
